[
  {
    "timestamp": "2026-07-03T23:43:36.535Z",
    "trigger": "manual",
    "target": "paid",
    "sentCount": 1,
    "details": [
      "[01:43:36] ⏳ Початок розсилки занять (тригер: Вручну)...",
      "[01:43:36] 👥 Знайдено користувачів для розсилки: 2 (Ціль: Лише оплачені)",
      "[01:43:36] ⚠️ Повідомлення для antigravity_test_user не відправлено в Telegram (користувач заблокував бота або невірний ID).",
      "[01:43:36] ✅ [День 2] успішно надіслано користувачу Alex_Frosti. Встановлено наступний день: 3",
      "[01:43:36] 🚀 Розсилку завершено! Всього успішно відправлено: 1 користувачам."
    ]
  },
  {
    "timestamp": "2026-07-03T23:42:45.488Z",
    "trigger": "manual",
    "target": "paid",
    "sentCount": 1,
    "details": [
      "[01:42:45] ⏳ Початок розсилки занять (тригер: Вручну)...",
      "[01:42:45] 👥 Знайдено користувачів для розсилки: 2 (Ціль: Лише оплачені)",
      "[01:42:45] ⚠️ Повідомлення для antigravity_test_user не відправлено в Telegram (користувач заблокував бота або невірний ID).",
      "[01:42:45] ✅ [День 1] успішно надіслано користувачу Alex_Frosti. Встановлено наступний день: 2",
      "[01:42:45] 🚀 Розсилку завершено! Всього успішно відправлено: 1 користувачам."
    ]
  },
  {
    "timestamp": "2026-07-03T23:42:46.379Z",
    "trigger": "auto",
    "target": "paid",
    "sentCount": 4,
    "details": [
      "[09:00:00] ⏳ Запуск щоденного планувальника розсилок (course_broadcast)...",
      "[09:00:02] ✅ Надіслано День 7 для @olena_koval (Пакет VIP). Встановлено наступний день: 8",
      "[09:00:03] ✅ Надіслано День 4 для @mariya_shvets (Пакет Супровід). Встановлено наступний день: 5",
      "[09:00:04] ✅ Надіслано День 2 для @kateryna_p (Пакет Базовий). Встановлено наступний день: 3",
      "[09:00:05] ✅ Надіслано День 3 для @natalia_k (Пакет Базовий). Встановлено наступний день: 4",
      "[09:00:07] 🎉 Щоденна розсилка успішно завершена."
    ]
  }
]